ekca_service/plugins/password/ldap3/__about__.py
ekca_service/plugins/password/ldap3/__init__.py
ekca_service/plugins/password/ldap3/__pycache__/__about__.cpython-37.opt-1.pyc
ekca_service/plugins/password/ldap3/__pycache__/__init__.cpython-37.opt-1.pyc
ekca_plugin_ldap3-0.1.7.dist-info/LICENSE
ekca_plugin_ldap3-0.1.7.dist-info/METADATA
ekca_plugin_ldap3-0.1.7.dist-info/WHEEL
ekca_plugin_ldap3-0.1.7.dist-info/entry_points.txt
ekca_plugin_ldap3-0.1.7.dist-info/top_level.txt
ekca_plugin_ldap3-0.1.7.dist-info/RECORD
